LICENSE
socketsecurity/__init__.py
socketsecurity/config.py
socketsecurity/output.py
socketsecurity/socketcli.py
socketsecurity/core/__init__.py
socketsecurity/core/classes.py
socketsecurity/core/cli_client.py
socketsecurity/core/exceptions.py
socketsecurity/core/git_interface.py
socketsecurity/core/lazy_file_loader.py
socketsecurity/core/logging.py
socketsecurity/core/messages.py
socketsecurity/core/resource_utils.py
socketsecurity/core/scm_comments.py
socketsecurity/core/socket_config.py
socketsecurity/core/utils.py
socketsecurity/core/helper/__init__.py
socketsecurity/core/helper/socket_facts_loader.py
socketsecurity/core/scm/__init__.py
socketsecurity/core/scm/base.py
socketsecurity/core/scm/client.py
socketsecurity/core/scm/github.py
socketsecurity/core/scm/gitlab.py
socketsecurity/core/tools/reachability.py
socketsecurity/plugins/__init__.py
socketsecurity/plugins/base.py
socketsecurity/plugins/jira.py
socketsecurity/plugins/manager.py
socketsecurity/plugins/slack.py
socketsecurity/plugins/teams.py
socketsecurity/plugins/webhook.py
socketsecurity/plugins/formatters/__init__.py
socketsecurity/plugins/formatters/slack.py
socketsecurity-2.2.71.dist-info/METADATA
socketsecurity-2.2.71.dist-info/WHEEL
socketsecurity-2.2.71.dist-info/entry_points.txt
socketsecurity-2.2.71.dist-info/licenses/LICENSE
socketsecurity-2.2.71.dist-info/RECORD
