Metadata-Version: 2.4
Name: socketsecurity
Version: 2.2.71
Summary: Socket Security CLI for CI/CD
Project-URL: Homepage, https://socket.dev
Author-email: Douglas Coburn <douglas@socket.dev>
Maintainer-email: Douglas Coburn <douglas@socket.dev>
License: MIT License
License-File: LICENSE
Keywords: oss,sca,security,socket.dev,socketsecurity
Classifier: Development Status :: 4 - Beta
Classifier: Intended Audience :: Developers
Classifier: Programming Language :: Python :: 3.11
Classifier: Programming Language :: Python :: 3.12
Requires-Python: >=3.10
Requires-Dist: bs4>=0.0.2
Requires-Dist: gitpython
Requires-Dist: markdown>=3.10
Requires-Dist: mdutils
Requires-Dist: packaging
Requires-Dist: prettytable
Requires-Dist: python-dotenv
Requires-Dist: requests
Requires-Dist: socketdev<4.0.0,>=3.0.29
Provides-Extra: dev
Requires-Dist: hatch; extra == 'dev'
Requires-Dist: pre-commit; extra == 'dev'
Requires-Dist: ruff>=0.3.0; extra == 'dev'
Requires-Dist: twine; extra == 'dev'
Requires-Dist: uv>=0.1.0; extra == 'dev'
Provides-Extra: test
Requires-Dist: pytest-asyncio>=0.23.0; extra == 'test'
Requires-Dist: pytest-cov>=4.1.0; extra == 'test'
Requires-Dist: pytest-mock>=3.12.0; extra == 'test'
Requires-Dist: pytest-watch>=4.2.0; extra == 'test'
Requires-Dist: pytest>=7.4.0; extra == 'test'
